{
	"animations": [
		{
			"loop": false,
			"offsets": [
				74,
				-30
			],
			"anim": "singDOWN",
			"fps": 24,
			"name": "down",
			"indices": []
		},
		{
			"loop": false,
			"offsets": [
				55,
				3
			],
			"anim": "singUP",
			"fps": 24,
			"name": "up",
			"indices": []
		},
		{
			"loop": false,
			"offsets": [
				93,
				-10
			],
			"anim": "singLEFT",
			"fps": 24,
			"name": "left",
			"indices": []
		},
		{
			"loop": false,
			"offsets": [
				43,
				-20
			],
			"anim": "singRIGHT",
			"fps": 24,
			"name": "right",
			"indices": []
		},
		{
			"loop": false,
			"offsets": [
				57,
				-8
			],
			"anim": "idle",
			"fps": 24,
			"name": "idle",
			"indices": []
		}
	],
	"no_antialiasing": false,
	"image": "CandyShop/Characters/Skid/D1/SkidStage1",
	"position": [
		0,
		350
	],
	"healthicon": "SkidD1S1",
	"flip_x": true,
	"healthbar_colors": [
		180,
		180,
		180
	],
	"camera_position": [
		350,
		100
	],
	"sing_duration": 4,
	"scale": 1
}